tmcsh/__init__.py
tmcsh/cli.py
tmcsh/device_chooser.py
tmcsh/tmc_callbacks.py
tmcsh-0.1.0.dist-info/METADATA
tmcsh-0.1.0.dist-info/WHEEL
tmcsh-0.1.0.dist-info/entry_points.txt
tmcsh-0.1.0.dist-info/top_level.txt
tmcsh-0.1.0.dist-info/RECORD
