Metadata-Version: 2.1
Name: tmcsh
Version: 0.1.0
Summary: "Interactive command shell for USB TMC device"
Home-page: https://github.com/Enchan1207/tmcsh
Author: Enchan1207
License: MIT
Requires-Dist: python-usbtmc
